threepio/__init__.py
threepio/bin/3pio
threepio/binaries/3pio-darwin-amd64
threepio/binaries/3pio-darwin-arm64
threepio/binaries/3pio-linux-amd64
threepio/binaries/3pio-linux-arm64
threepio/binaries/3pio-windows-amd64.exe
threepio_test_runner-0.8.0.dist-info/METADATA
threepio_test_runner-0.8.0.dist-info/WHEEL
threepio_test_runner-0.8.0.dist-info/entry_points.txt
threepio_test_runner-0.8.0.dist-info/top_level.txt
threepio_test_runner-0.8.0.dist-info/RECORD
