Metadata-Version: 2.4
Name: threepio-test-runner
Version: 0.8.0
Summary: Context-optimized test runner for coding agents
Home-page: https://github.com/zk/3pio
Author: Zachary Kim
Author-email: zachary@example.com
License: MIT
Project-URL: Bug Reports, https://github.com/zk/3pio/issues
Project-URL: Source, https://github.com/zk/3pio
Keywords: test testing pytest ai adapter reporter
Classifier: Development Status :: 3 - Alpha
Classifier: Intended Audience :: Developers
Classifier: License :: OSI Approved :: MIT License
Classifier: Programming Language :: Python :: 3
Classifier: Programming Language :: Python :: 3.8
Classifier: Programming Language :: Python :: 3.9
Classifier: Programming Language :: Python :: 3.10
Classifier: Programming Language :: Python :: 3.11
Classifier: Programming Language :: Python :: 3.12
Classifier: Topic :: Software Development :: Testing
Classifier: Topic :: Software Development :: Libraries
Requires-Python: >=3.8
Dynamic: author
Dynamic: author-email
Dynamic: classifier
Dynamic: description
Dynamic: description-content-type
Dynamic: home-page
Dynamic: keywords
Dynamic: license
Dynamic: project-url
Dynamic: requires-python
Dynamic: summary
